.gitignore
VERSIONS.yaml
build.sh
setup.py
upload.sh
bin/sirem
sirem/__init__.py
sirem/github-pandoc.css
sirem/report.template.html
sirem/report.template.md
sirem/sirem.py
sirem.egg-info/PKG-INFO
sirem.egg-info/SOURCES.txt
sirem.egg-info/dependency_links.txt
sirem.egg-info/requires.txt
sirem.egg-info/top_level.txt