Metadata-Version: 1.0
Name: sirem
Version: 0.0.7
Summary: SImple RElease Manager tool
Home-page: UNKNOWN
Author: Eyal Firstenberg
Author-email: eyalfir@gmail.com
License: UNKNOWN
Platform: UNKNOWN
